hydro_quebec_api_wrapper-4.1.0.dist-info/licenses/LICENSE
hydroqc/__init__.py
hydroqc/account.py
hydroqc/consts.py
hydroqc/customer.py
hydroqc/diagnostic.py
hydroqc/error.py
hydroqc/logger.py
hydroqc/public_client.py
hydroqc/py.typed
hydroqc/timerange.py
hydroqc/utils.py
hydroqc/webuser.py
hydroqc/contract/__init__.py
hydroqc/contract/common.py
hydroqc/contract/contract_d.py
hydroqc/contract/contract_d_cpc.py
hydroqc/contract/contract_dpc.py
hydroqc/contract/contract_dt.py
hydroqc/contract/contract_m.py
hydroqc/contract/contract_m_gdp.py
hydroqc/contract/contract_residential.py
hydroqc/contract/outage.py
hydroqc/hydro_api/__init__.py
hydroqc/hydro_api/cache.py
hydroqc/hydro_api/client.py
hydroqc/hydro_api/consts.py
hydroqc/peak/__init__.py
hydroqc/peak/basepeak.py
hydroqc/peak/basepeakhandler.py
hydroqc/peak/consts.py
hydroqc/peak/cpc/__init__.py
hydroqc/peak/cpc/consts.py
hydroqc/peak/cpc/handler.py
hydroqc/peak/cpc/peak.py
hydroqc/peak/dpc/__init__.py
hydroqc/peak/dpc/consts.py
hydroqc/peak/dpc/handler.py
hydroqc/peak/dpc/peak.py
hydroqc/types/__init__.py
hydroqc/types/account.py
hydroqc/types/common.py
hydroqc/types/consump.py
hydroqc/types/contract.py
hydroqc/types/cpc.py
hydroqc/types/dpc.py
hydroqc/types/dt.py
hydroqc/types/outage.py
hydro_quebec_api_wrapper-4.1.0.dist-info/METADATA
hydro_quebec_api_wrapper-4.1.0.dist-info/WHEEL
hydro_quebec_api_wrapper-4.1.0.dist-info/entry_points.txt
hydro_quebec_api_wrapper-4.1.0.dist-info/top_level.txt
hydro_quebec_api_wrapper-4.1.0.dist-info/RECORD
