Metadata-Version: 2.4
Name: Hydro-Quebec-API-Wrapper
Version: 4.1.0
Summary: A wrapper library to access hydro quebec API and more
Home-page: https://hydroqc.ca
Author-email: Hydroqc Team <info@hydroqc.ca>
License: LGPL-3.0-or-later
Project-URL: Source Code, https://gitlab.com/hydroqc/hydroqc
Project-URL: Bug Reports, https://gitlab.com/hydroqc/hydroqc/-/issues
Project-URL: Home-page, https://hydroqc.ca
Keywords: hydroquebec,lib
Platform: any
Classifier: Programming Language :: Python :: 3
Classifier: Operating System :: OS Independent
Requires-Python: >=3.13.0
License-File: LICENSE
Requires-Dist: aiohttp==3.13.2
Requires-Dist: python-dateutil==2.9.0.post0
Requires-Dist: pytz==2025.2
Requires-Dist: aiocache==0.12.3
Requires-Dist: pkce==1.0.3
Dynamic: license-file
